one_py_sdk/__init__.py
one_py_sdk/clientsdk.py
one_py_sdk/common/__init__.py
one_py_sdk/common/configuration.py
one_py_sdk/common/library.py
one_py_sdk/enterprise/__init__.py
one_py_sdk/enterprise/authentication.py
one_py_sdk/enterprise/core.py
one_py_sdk/enterprise/report.py
one_py_sdk/enterprise/twin.py
one_py_sdk/historian/__init__.py
one_py_sdk/historian/data.py
one_py_sdk/operations/__init__.py
one_py_sdk/operations/spreadsheet.py
one_py_sdk/shared/__init__.py
one_py_sdk/shared/constants.py
one_py_sdk/shared/helpers/__init__.py
one_py_sdk/shared/helpers/csvhelper.py
one_py_sdk/shared/helpers/datetimehelper.py
one_py_sdk/shared/helpers/helpers.py
one_py_sdk/shared/helpers/protobufhelper.py
one_py_sdk/shared/models/datapoint.py
one_py_sdk/tests/sdkTests.py
one_py_sdk/tests/testConstants.py
one_py_sdk-1.9.2.dist-info/licenses/LICENSE
one_py_sdk-1.9.2.dist-info/METADATA
one_py_sdk-1.9.2.dist-info/WHEEL
one_py_sdk-1.9.2.dist-info/top_level.txt
one_py_sdk-1.9.2.dist-info/RECORD
