Metadata-Version: 2.4
Name: one_py_sdk
Version: 1.9.2
Summary: A package to interact with the ONE waterquality platform APIs.
Author-email: AquaticInformatics <daniel.edwards@aquaticinformatics.com>
License: Copyright (c) 2018 The Python Packaging Authority
Project-URL: Homepage, https://github.com/AquaticInformatics/ONE-Py-SDK
Project-URL: Bug Tracker, https://github.com/AquaticInformatics/ONE-Py-SDK/issues
Project-URL: Sample Code, https://github.com/AquaticInformatics/one-py-samples
Classifier: Programming Language :: Python :: 3
Classifier: License :: OSI Approved :: MIT License
Classifier: Operating System :: OS Independent
Requires-Python: >=3.7
License-File: LICENSE
Requires-Dist: requests
Requires-Dist: protobuf==3.20.1
Requires-Dist: one_interfaces
Requires-Dist: requests_cache
Requires-Dist: pytz
Dynamic: license-file
